setup.cfg
setup.py
pyterminfo/__init__.py
pyterminfo/ast.py
pyterminfo/ast_transforms.py
pyterminfo/cfg.py
pyterminfo/cfg_transforms.py
pyterminfo/compile.py
pyterminfo/constants.py
pyterminfo/core.py
pyterminfo/ops.py
pyterminfo/parser.py
pyterminfo/serialization.py
pyterminfo/utils.py
pyterminfo/visualization.py
pyterminfo.egg-info/PKG-INFO
pyterminfo.egg-info/SOURCES.txt
pyterminfo.egg-info/dependency_links.txt
pyterminfo.egg-info/requires.txt
pyterminfo.egg-info/top_level.txt