Metadata-Version: 1.1
Name: pyterminfo
Version: 0.1
Summary: a terminfo-to-python cross compiler
Home-page: https://github.com/zachariahreed/pyterminfo
Author: Zachariah Reed
Author-email: zreed@fastmail.com
License: GPL
Download-URL: https://github.com/zachariahreed/pyterminfo/tarball/0.1
Platform: any
Classifier: Development Status :: 4 - Beta
Classifier: Intended Audience :: Developers
Classifier: License :: OSI Approved :: GNU General Public License v3 or later (GPLv3+)
Classifier: Environment :: Console
Classifier: Operating System :: Unix
Classifier: Programming Language :: Python :: 3 :: Only
Classifier: Programming Language :: Python :: 3.4
Classifier: Programming Language :: Python :: 3.5
Classifier: Topic :: Terminals
